Workbook

Sheet Cotation
A1: Code | B1: Thème | C1: Exigence de l'expert | D1: Verdict | E1: Preuve dans le code | F1: Écart constaté | G1: Charge (j) | H1: Priorité
A2: EXP-01 | B2: Ouverture et états de caisse | C2: Message d'accueil "Bonjour : Connectez-vous" à caisse fermée | D2: KO | E2: lock.html:67 | F2: Libellé actuel : "Cette caisse est actuellement inutilisable" | G2: 0.2 | H2: P1
A3: EXP-02 | B3: Ouverture et états de caisse | C3: Affichage du fond de caisse théorique à l'ouverture | D3: PARTIEL | E3: CashSessionResource.java:81 | F3: Le formulaire pré-remplit le paramètre cash.default-opening-float ; aucun théorique calculé (report de clôture, coffre) | G3: 1 | H3: P2
A4: EXP-03 | B4: Ouverture et états de caisse | C4: Libellé d'attente "CLIENT SUIVANT" | D4: KO | E4: ticket.html:51 | F4: Libellé actuel : "EN ATTENTE D'ARTICLES..." | G4: 0.2 | H4: P1
A5: EXP-04 | B5: Ouverture et états de caisse | C5: Comptage du fond en mode calculatrice, rien n'est enregistré | D5: PARTIEL | E5: CashCountService.java:29 | F5: La calculatrice par coupure existe mais n'est offerte qu'à la clôture et son résultat est enregistré ; billets au-delà de 50 EUR absents | G5: 1.5 | H5: P1
A6: EXP-05 | B6: Ouverture et états de caisse | C6: Code caissier en chiffres ou en lettres, puis code secret | D6: OK | E6: lock.html:76 | F6: Deux modes : PIN rapide et identifiant alphabétique en deux étapes | G6: 0 | H6: -
A7: EXP-06 | B7: Ouverture et états de caisse | C7: Affichage du matériel disponible à la prise de poste | D7: OK | E7: AuthResource.java:142 | F7: Toute prise de poste passe par la page d'état matériel, CONTINUER étant le seul passage | G7: 0 | H7: -
A8: EXP-07 | B8: Ouverture et états de caisse | C8: Ouverture du tiroir pour installer le fond | D8: OK | E8: AuthResource.java:198 | F8: Sous le paramètre drawer.open-on-login (BO-10-02-25) | G8: 0 | H8: -
A9: EXP-08 | B9: Ouverture et états de caisse | C9: Encaissement impossible tiroir ouvert | D9: OK | E9: DrawerCheckFilter.java:52 | F9: Filtre global, détournement vers l'écran TIROIR OUVERT et retour automatique | G9: 0 | H9: -
A10: EXP-09 | B10: Ouverture et états de caisse | C10: Seconde ouverture sans revalidation du fond | D10: OK | E10: CashSessionService.java:264 | F10: Une session ouverte fait repartir directement en vente | G10: 0 | H10: -
A11: EXP-10 | B11: Ouverture et états de caisse | C11: Trois notions : verrouiller/déverrouiller (pause, ticket conservé), ouvrir/fermer sa caisse (retrait du tiroir, la réouverture continue la session du matin), clôturer (comptage, prélèvement de tous les moyens, RAZ de fin de poste) | D11: PARTIEL | E11: CashSessionResource.java:165 / AuthResource.java:228 | F11: La clôture Z existe et est correcte ; il manque la fermeture sans clôture, et la déconnexion qui en tient lieu doit disparaître | G11: 3.5 | H11: P1
A12: EXP-11 | B12: Ouverture et états de caisse | C12: Fermeture impossible pendant une transaction | D12: KO | E12: SessionCloseService.java:79 | F12: Aucun contrôle du ticket en cours : la déconnexion vide le panier | G12: 0.5 | H12: P1
A13: EXP-12 | B13: Ouverture et états de caisse | C13: Verrouillage : tiroir bloqué, message CAISSE VERROUILLÉE, possible en cours de ticket | D13: PARTIEL | E13: LockCheckFilter.java:99 | F13: Le verrouillage existe mais affiche CAISSE FERMÉE et ABANDONNE le ticket en cours | G13: 1.5 | H13: P1
... A97: EXP-94 | B97: Fonctions avancées | C97: Mode école avec début et fin sous autorisation | D97: OK | E97: HomeService.java:459 | F97: Début et fin journalisés, aval manager, thème dédié, gestes fiscaux bloqués | G97: 0 | H97: -

Sheet Synthèse
A1: Cotation du rapport de test — expert fonctionnel caisse
A2: Source : 2026-09-28-HENRI-CAISSE.txt — 94 exigences relevées, cotées contre le code d'impos
A3: Verdict | B3: Nombre | C3: Part | D3: Charge (j)
A4: OK | B4: =COUNTIF(Cotation!$D$2:$D$97,"OK") -> 43 | C4: =B4/$B$7 -> 0.44791667 | D4: =SUMIFS(Cotation!$G$2:$G$97,Cotation!$D$2:$D$97,"OK") -> 0.6
A5: PARTIEL | B5: =COUNTIF(Cotation!$D$2:$D$97,"PARTIEL") -> 32 | C5: =B5/$B$7 -> 0.33333333 | D5: =SUMIFS(Cotation!$G$2:$G$97,Cotation!$D$2:$D$97,"PARTIEL") -> 62
A6: KO | B6: =COUNTIF(Cotation!$D$2:$D$97,"KO") -> 21 | C6: =B6/$B$7 -> 0.21875 | D6: =SUMIFS(Cotation!$G$2:$G$97,Cotation!$D$2:$D$97,"KO") -> 63.9
A7: Total | B7: =SUM(B4:B6) -> 96 | C7: =SUM(C4:C6) -> 1 | D7: =SUM(D4:D6) -> 126.5
A9: Taux de couverture (PARTIEL compté pour moitié) | B9: =(B4+B5/2)/B7 -> 0.61458333
A10: Charge totale des écarts | B10: =D7 -> 126.5
A12: Par priorité
A13: Priorité | B13: Nombre | C13: Charge (j)
A14: P1 | B14: =COUNTIF(Cotation!$H$2:$H$97,"P1") -> 26 | C14: =SUMIFS(Cotation!$G$2:$G$97,Cotation!$H$2:$H$97,"P1") -> 43.4
A15: P2 | B15: =COUNTIF(Cotation!$H$2:$H$97,"P2") -> 29 | C15: =SUMIFS(Cotation!$G$2:$G$97,Cotation!$H$2:$H$97,"P2") -> 83.1
A16: P3 | B16: =COUNTIF(Cotation!$H$2:$H$97,"P3") -> 0 | C16: =SUMIFS(Cotation!$G$2:$G$97,Cotation!$H$2:$H$97,"P3") -> 0
A17: Total | B17: =SUM(B14:B16) -> 55 | C17: =SUM(C14:C16) -> 126.5
A19: Par thème
A20: Thème | B20: OK | C20: PARTIEL | D20: KO | E20: Charge (j)
A21: Fidélité | B21: =COUNTIFS(Cotation!$B$2:$B$97,$A21,Cotation!$D$2:$D$97,"OK") -> 1 | C21: =COUNTIFS(Cotation!$B$2:$B$97,$A21,Cotation!$D$2:$D$97,"PARTIEL") -> 2 | D21: =COUNTIFS(Cotation!$B$2:$B$97,$A21,Cotation!$D$2:$D$97,"KO") -> 0 | E21: =SUMIFS(Cotation!$G$2:$G$97,Cotation!$B$2:$B$97,$A21) -> 2.5
A22: Fonctions avancées | B22: =COUNTIFS(Cotation!$B$2:$B$97,$A22,Cotation!$D$2:$D$97,"OK") -> 3 | C22: =COUNTIFS(Cotation!$B$2:$B$97,$A22,Cotation!$D$2:$D$97,"PARTIEL") -> 3 | D22: =COUNTIFS(Cotation!$B$2:$B$97,$A22,Cotation!$D$2:$D$97,"KO") -> 5 | E22: =SUMIFS(Cotation!$G$2:$G$97,Cotation!$B$2:$B$97,$A22) -> 33
A23: Messages | B23: =COUNTIFS(Cotation!$B$2:$B$97,$A23,Cotation!$D$2:$D$97,"OK") -> 0 | C23: =COUNTIFS(Cotation!$B$2:$B$97,$A23,Cotation!$D$2:$D$97,"PARTIEL") -> 1 | D23: =COUNTIFS(Cotation!$B$2:$B$97,$A23,Cotation!$D$2:$D$97,"KO") -> 1 | E23: =SUMIFS(Cotation!$G$2:$G$97,Cotation!$B$2:$B$97,$A23) -> 5
A24: Monnaie et mouvements | B24: =COUNTIFS(Cotation!$B$2:$B$97,$A24,Cotation!$D$2:$D$97,"OK") -> 2 | C24: =COUNTIFS(Cotation!$B$2:$B$97,$A24,Cotation!$D$2:$D$97,"PARTIEL") -> 1 | D24: =COUNTIFS(Cotation!$B$2:$B$97,$A24,Cotation!$D$2:$D$97,"KO") -> 1 | E24: =SUMIFS(Cotation!$G$2:$G$97,Cotation!$B$2:$B$97,$A24) -> 3.5
A25: Négatif et superviseur | B25: =COUNTIFS(Cotation!$B$2:$B$97,$A25,Cotation!$D$2:$D$97,"OK") -> 3 | C25: =COUNTIFS(Cotation!$B$2:$B$97,$A25,Cotation!$D$2:$D$97,"PARTIEL") -> 4 | D25: =COUNTIFS(Cotation!$B$2:$B$97,$A25,Cotation!$D$2:$D$97,"KO") -> 4 | E25: =SUMIFS(Cotation!$G$2:$G$97,Cotation!$B$2:$B$97,$A25) -> 20.5
A26: Ouverture et états de caisse | B26: =COUNTIFS(Cotation!$B$2:$B$97,$A26,Cotation!$D$2:$D$97,"OK") -> 5 | C26: =COUNTIFS(Cotation!$B$2:$B$97,$A26,Cotation!$D$2:$D$97,"PARTIEL") -> 5 | D26: =COUNTIFS(Cotation!$B$2:$B$97,$A26,Cotation!$D$2:$D$97,"KO") -> 5 | E26: =SUMIFS(Cotation!$G$2:$G$97,Cotation!$B$2:$B$97,$A26) -> 12.4
A27: Remises | B27: =COUNTIFS(Cotation!$B$2:$B$97,$A27,Cotation!$D$2:$D$97,"OK") -> 5 | C27: =COUNTIFS(Cotation!$B$2:$B$97,$A27,Cotation!$D$2:$D$97,"PARTIEL") -> 0 | D27: =COUNTIFS(Cotation!$B$2:$B$97,$A27,Cotation!$D$2:$D$97,"KO") -> 0 | E27: =SUMIFS(Cotation!$G$2:$G$97,Cotation!$B$2:$B$97,$A27) -> 0
A28: Règlements | B28: =COUNTIFS(Cotation!$B$2:$B$97,$A28,Cotation!$D$2:$D$97,"OK") -> 12 | C28: =COUNTIFS(Cotation!$B$2:$B$97,$A28,Cotation!$D$2:$D$97,"PARTIEL") -> 5 | D28: =COUNTIFS(Cotation!$B$2:$B$97,$A28,Cotation!$D$2:$D$97,"KO") -> 2 | E28: =SUMIFS(Cotation!$G$2:$G$97,Cotation!$B$2:$B$97,$A28) -> 18
A29: Saisie article | B29: =COUNTIFS(Cotation!$B$2:$B$97,$A29,Cotation!$D$2:$D$97,"OK") -> 7 | C29: =COUNTIFS(Cotation!$B$2:$B$97,$A29,Cotation!$D$2:$D$97,"PARTIEL") -> 4 | D29: =COUNTIFS(Cotation!$B$2:$B$97,$A29,Cotation!$D$2:$D$97,"KO") -> 0 | E29: =SUMIFS(Cotation!$G$2:$G$97,Cotation!$B$2:$B$97,$A29) -> 5.8
A30: Ticket | B30: =COUNTIFS(Cotation!$B$2:$B$97,$A30,Cotation!$D$2:$D$97,"OK") -> 2 | C30: =COUNTIFS(Cotation!$B$2:$B$97,$A30,Cotation!$D$2:$D$97,"PARTIEL") -> 3 | D30: =COUNTIFS(Cotation!$B$2:$B$97,$A30,Cotation!$D$2:$D$97,"KO") -> 2 | E30: =SUMIFS(Cotation!$G$2:$G$97,Cotation!$B$2:$B$97,$A30) -> 14.3
A31: Tiroir et fin de journée | B31: =COUNTIFS(Cotation!$B$2:$B$97,$A31,Cotation!$D$2:$D$97,"OK") -> 3 | C31: =COUNTIFS(Cotation!$B$2:$B$97,$A31,Cotation!$D$2:$D$97,"PARTIEL") -> 4 | D31: =COUNTIFS(Cotation!$B$2:$B$97,$A31,Cotation!$D$2:$D$97,"KO") -> 1 | E31: =SUMIFS(Cotation!$G$2:$G$97,Cotation!$B$2:$B$97,$A31) -> 11.5
A32: Note : la charge est une estimation de développement sur impos seul, hors nœud magasin et hors back-office, saisie manuellement ligne à ligne dans l'onglet Cotation.
